spektral/__init__.py
spektral/data/__init__.py
spektral/data/dataset.py
spektral/data/graph.py
spektral/data/loaders.py
spektral/data/utils.py
spektral/datasets/__init__.py
spektral/datasets/citation.py
spektral/datasets/dblp.py
spektral/datasets/flickr.py
spektral/datasets/graphsage.py
spektral/datasets/mnist.py
spektral/datasets/modelnet.py
spektral/datasets/ogb.py
spektral/datasets/qm7.py
spektral/datasets/qm9.py
spektral/datasets/tudataset.py
spektral/datasets/utils.py
spektral/layers/__init__.py
spektral/layers/base.py
spektral/layers/convolutional/__init__.py
spektral/layers/convolutional/agnn_conv.py
spektral/layers/convolutional/appnp_conv.py
spektral/layers/convolutional/arma_conv.py
spektral/layers/convolutional/censnet_conv.py
spektral/layers/convolutional/cheb_conv.py
spektral/layers/convolutional/conv.py
spektral/layers/convolutional/crystal_conv.py
spektral/layers/convolutional/diffusion_conv.py
spektral/layers/convolutional/ecc_conv.py
spektral/layers/convolutional/edge_conv.py
spektral/layers/convolutional/gat_conv.py
spektral/layers/convolutional/gated_graph_conv.py
spektral/layers/convolutional/gcn_conv.py
spektral/layers/convolutional/gcs_conv.py
spektral/layers/convolutional/general_conv.py
spektral/layers/convolutional/gin_conv.py
spektral/layers/convolutional/graphsage_conv.py
spektral/layers/convolutional/gtv_conv.py
spektral/layers/convolutional/message_passing.py
spektral/layers/convolutional/tag_conv.py
spektral/layers/convolutional/xenet_conv.py
spektral/layers/ops/__init__.py
spektral/layers/ops/graph.py
spektral/layers/ops/matmul.py
spektral/layers/ops/modes.py
spektral/layers/ops/ops.py
spektral/layers/ops/scatter.py
spektral/layers/ops/sparse.py
spektral/layers/pooling/__init__.py
spektral/layers/pooling/asym_cheeger_cut_pool.py
spektral/layers/pooling/diff_pool.py
spektral/layers/pooling/dmon_pool.py
spektral/layers/pooling/global_pool.py
spektral/layers/pooling/just_balance_pool.py
spektral/layers/pooling/la_pool.py
spektral-1.3.1.dist-info/LICENSE
spektral-1.3.1.dist-info/METADATA
spektral-1.3.1.dist-info/WHEEL
spektral-1.3.1.dist-info/top_level.txt
spektral-1.3.1.dist-info/RECORD
