Metadata-Version: 2.1
Name: spektral
Version: 1.3.1
Summary: Graph Neural Networks with Keras and TensorFlow.
Author-email: Daniele Grattarola <daniele.grattarola@gmail.com>
Project-URL: homepage, https://github.com/danielegrattarola/spektral
Project-URL: documentation, https://graphneural.network
Classifier: Programming Language :: Python :: 3
Classifier: License :: OSI Approved :: MIT License
Classifier: Operating System :: OS Independent
Requires-Python: >=3.7
License-File: LICENSE
Requires-Dist: joblib
Requires-Dist: lxml
Requires-Dist: networkx
Requires-Dist: numpy
Requires-Dist: pandas
Requires-Dist: requests
Requires-Dist: scikit-learn
Requires-Dist: scipy
Requires-Dist: tqdm
Requires-Dist: tensorflow >=2.2.0 ; platform_machine != "arm64" or platform_system != "Darwin"
Requires-Dist: tensorflow-macos >=2.5.0 ; platform_machine == "arm64" and platform_system == "Darwin"
